dimentyy/tl/parse/__init__.py
dimentyy/tl/parse/container.py
dimentyy/tl/parse/new_html.py
dimentyy_tl_parse-0.0.1.dev5.dist-info/METADATA
dimentyy_tl_parse-0.0.1.dev5.dist-info/WHEEL
dimentyy_tl_parse-0.0.1.dev5.dist-info/licenses/LICENSE.md
dimentyy_tl_parse-0.0.1.dev5.dist-info/RECORD
