Metadata-Version: 2.3
Name: dimentyy.tl-parse
Version: 0.0.1.dev5
Summary: Better parsing modes for telethon.TelegramClient
Project-URL: Source, https://github.com/dimentyy/tl-parse.py
Project-URL: Author, https://t.me/dimentyy
Author: dimentyy
License-Expression: MIT
License-File: LICENSE.md
Classifier: License :: OSI Approved :: MIT License
Classifier: Programming Language :: Python :: 3
Requires-Dist: telethon
